{
"application":
[{"name":"name","value":"aspdotnet_demo"},
{"name":"description","value":"Demo ASP.NET core application generated by realMethods"},
{"name":"author","value":"dev@realmehods.com"},
{"name":"corporate logo URL","value":""},
{"name":"application logo URL","value":"./img/turnstone.biologics.png"},
{"name":"company name","value":"Turnstone Biologics"},
{"name":"version","value":"0.0.1"},
{"name":"package name","value":"com.occulue"}],
"nuget":
[{"name":"serverUrl","value":"https://cloudmigrate.jfrog.io/cloudmigrate"},
{"name":"userName","value":"admin"},
{"name":"password","value":"Ex3Mc5Ma7Lh8Fu"},
{"name":"repoKey","value":"local-nuget-repo"},
{"name":"licenseUrl","value":""},
{"name":"projectUrl","value":"https://bitbucket.org/tylertravismya/aspnetcore/src"},
{"name":"iconUrl","value":""},
{"name":"releaseNotes","value":""},
{"name":"copyRight","value":"Copyright 2019"},
{"name":"tags","value":""},
{"name":"requireLicenseAcceptance","value":"false"}],
"hibernate":
[{"name":"connection.driver.class","value":"NHibernate.Driver.MySqlDataDriver"},
{"name":"connection.database","value":"test"},
{"name":"connection.username","value":"root"},
{"name":"connection.password","value":"6969Cutlass!!"},
{"name":"dialect","value":"NHibernate.Dialect.MySQLDialect"}]}
